winmail/ComApi.py
winmail/Winmail.py
winmail/__init__.py
winmail/OpenApi/ApiBase.py
winmail/OpenApi/OpenApi.py
winmail/OpenApi/__init__.py
winmail/OpenApi/Api12/ApiOpt.py
winmail/OpenApi/Api12/__init__.py
winmail/utils/MysqlClass.py
winmail/utils/Other.py
winmail/utils/PostgreClass.py
winmail/utils/SqliteClass.py
winmail/utils/__init__.py
winmail-2023.11.21.dist-info/METADATA
winmail-2023.11.21.dist-info/WHEEL
winmail-2023.11.21.dist-info/top_level.txt
winmail-2023.11.21.dist-info/RECORD
