Metadata-Version: 2.1
Name: winmail
Version: 2023.11.21
Summary: Winmail API
Home-page: http://winmail.cn
Author: Sway
Author-email: sway_wang@foxmail.com
License: UNKNOWN
Platform: UNKNOWN
Requires-Python: >=3.6.0
Requires-Dist: requests
Requires-Dist: PyMySQL
Requires-Dist: psycopg2
Requires-Dist: pydantic
Requires-Dist: pywin32 ; sys_platform == "win32"
